{
"type": "FeatureCollection",
"name": "example_3",
"crs": { "type": "name", "properties": { "name": "urn:ogc:def:crs:OGC:1.3:CRS84" } },
"features": [
{ "type": "Feature", "properties": { "@id": "node/8528104366", "zhv-dhid": "de:14628:3830:0:1", "zhv-name": 1, "osm-name": "Lauterbach Niedere Straße", "zhv-link": "https://www.openstreetmap.org/?mlat=51.07147&mlon=14.10525#map=19/51.07147/14.10525", "marker-color": "#ff0000" }, "geometry": { "type": "Point", "coordinates": [ 14.1053, 51.071497 ] } },
{ "type": "Feature", "properties": { "@id": null, "zhv-dhid": null, "zhv-name": null, "osm-name": null, "zhv-link": null, "marker-color": "#00ff00" }, "geometry": { "type": "Point", "coordinates": [ 14.1253, 51.074497 ] } }
]
}
